aliyunsdkairticketopen/__init__.py
aliyunsdkairticketopen/request/__init__.py
aliyunsdkairticketopen/request/v20230117/AccountFlowListRequest.py
aliyunsdkairticketopen/request/v20230117/AncillarySuggestRequest.py
aliyunsdkairticketopen/request/v20230117/BookRequest.py
aliyunsdkairticketopen/request/v20230117/CancelRequest.py
aliyunsdkairticketopen/request/v20230117/ChangeApplyRequest.py
aliyunsdkairticketopen/request/v20230117/ChangeCancelRequest.py
aliyunsdkairticketopen/request/v20230117/ChangeConfirmRequest.py
aliyunsdkairticketopen/request/v20230117/ChangeDetailListOfBuyerRequest.py
aliyunsdkairticketopen/request/v20230117/ChangeDetailListOfOrderNumRequest.py
aliyunsdkairticketopen/request/v20230117/ChangeDetailRequest.py
aliyunsdkairticketopen/request/v20230117/EnrichRequest.py
aliyunsdkairticketopen/request/v20230117/FileUploadRequest.py
aliyunsdkairticketopen/request/v20230117/FlightChangeOfOrderRequest.py
aliyunsdkairticketopen/request/v20230117/GetTokenRequest.py
aliyunsdkairticketopen/request/v20230117/OrderDetailRequest.py
aliyunsdkairticketopen/request/v20230117/OrderListRequest.py
aliyunsdkairticketopen/request/v20230117/PricingRequest.py
aliyunsdkairticketopen/request/v20230117/RefundApplyRequest.py
aliyunsdkairticketopen/request/v20230117/RefundDetailListRequest.py
aliyunsdkairticketopen/request/v20230117/RefundDetailRequest.py
aliyunsdkairticketopen/request/v20230117/SearchRequest.py
aliyunsdkairticketopen/request/v20230117/TicketingCheckRequest.py
aliyunsdkairticketopen/request/v20230117/TicketingRequest.py
aliyunsdkairticketopen/request/v20230117/__init__.py
aliyun_python_sdk_airticketopen-3.0.3.dist-info/LICENSE
aliyun_python_sdk_airticketopen-3.0.3.dist-info/METADATA
aliyun_python_sdk_airticketopen-3.0.3.dist-info/WHEEL
aliyun_python_sdk_airticketopen-3.0.3.dist-info/top_level.txt
aliyun_python_sdk_airticketopen-3.0.3.dist-info/RECORD
